fileimport_package/__init__.py
fileimport_package/fileimport_util.py
fileimport_util-1.0.dist-info/LICENSE
fileimport_util-1.0.dist-info/METADATA
fileimport_util-1.0.dist-info/WHEEL
fileimport_util-1.0.dist-info/top_level.txt
fileimport_util-1.0.dist-info/RECORD
