Metadata-Version: 2.1
Name: fileimport_util
Version: 1.0
Summary: A package that assist with imports via drag and dropping of files so end users can run scripts with ease
Author-email: Devin Akerley <devin.akerley@health.ny.gov>
Classifier: Programming Language :: Python :: 3
Classifier: License :: OSI Approved :: MIT License
Classifier: Operating System :: OS Independent
Requires-Python: >=3.8
License-File: LICENSE
